shleem/__init__.py
shleem/_version.py
shleem/core.py
shleem/exceptions.py
shleem/shared.py
shleem/mongodb/__init__.py
shleem/mongodb/mongodb.py
shleem/scripts/__init__.py
shleem/scripts/mongozen_cli.py
shleem/scripts/util_cli.py
shleem-0.0.2.dist-info/DESCRIPTION.rst
shleem-0.0.2.dist-info/METADATA
shleem-0.0.2.dist-info/RECORD
shleem-0.0.2.dist-info/WHEEL
shleem-0.0.2.dist-info/entry_points.txt
shleem-0.0.2.dist-info/metadata.json
shleem-0.0.2.dist-info/top_level.txt
tests/__init__.py
tests/test_core.py
tests/test_mongo.py
