Metadata-Version: 2.0
Name: shleem
Version: 0.0.2
Summary: Automate and version datasets generation from data sources.
Home-page: https://github.com/shaypal5/shleem
Author: Shay Palachy
Author-email: shay.palachy@gmail.com
License: UNKNOWN
Platform: UNKNOWN
Classifier: Development Status :: 4 - Beta
Classifier: License :: OSI Approved :: MIT License
Classifier: Programming Language :: Python
Classifier: Programming Language :: Python :: 3.4
Classifier: Programming Language :: Python :: 3.5
Classifier: Programming Language :: Python :: 3.6
Classifier: Topic :: Software Development :: Libraries
Classifier: Topic :: Software Development :: Libraries :: Python Modules
Classifier: Intended Audience :: Developers
Requires-Dist: pymongo (>=3.4)
Requires-Dist: strct
Provides-Extra: test
Requires-Dist: pytest; extra == 'test'
Requires-Dist: coverage; extra == 'test'
Requires-Dist: pytest-cov; extra == 'test'
Requires-Dist: pymongo (>=3.4); extra == 'test'
Requires-Dist: strct; extra == 'test'
